{
  "schemaVersion": 1,
  "capturedAt": "2026-07-23T18:17:30.4592559+02:00",
  "status": "pass",
  "totalTestsPassed": 5436,
  "suites": [
    {
      "name": "full monorepo Vitest regression suite (thread pool, single worker)",
      "testsPassed": 5436
    }
  ],
  "typechecks": [
    "@vai/desktop",
    "@vai/extension",
    "@vai/showcase",
    "@vai/contracts",
    "@vai/constants",
    "@vai/core",
    "@vai/runtime",
    "@vai/ui"
  ],
  "checks": [
    "corepack pnpm install --offline --frozen-lockfile",
    "node node_modules/vitest/vitest.mjs run --pool=threads --maxWorkers=1 (331 files passed; 1 skipped; 5,436 tests passed; 48 skipped)",
    "corepack pnpm -r --parallel typecheck",
    "corepack pnpm lint (0 errors; existing warnings only)",
    "node scripts/check-platform-constants.mjs",
    "corepack pnpm build",
    "cargo check --manifest-path apps/desktop/src-tauri/Cargo.toml",
    "post-build portability fix: 14 focused runtime tests and @vai/runtime typecheck"
  ]
}
